{
  "serverMaxRevisionCounter": 103,
  "sourceMembers": {
    "FlexiPage__OMConsole_UtilityBar": {
      "serverRevisionCounter": 1,
      "lastRetrievedFromServer": null,
      "memberType": "FlexiPage",
      "isNameObsolete": false
    },
    "AppMenu__AppSwitcher": {
      "serverRevisionCounter": 2,
      "lastRetrievedFromServer": null,
      "memberType": "AppMenu",
      "isNameObsolete": false
    },
    "Profile__Admin": {
      "serverRevisionCounter": 10,
      "lastRetrievedFromServer": null,
      "memberType": "Profile",
      "isNameObsolete": false
    },
    "ApexClass__B2BAuthorizeTokenizedPayment": {
      "serverRevisionCounter": 11,
      "lastRetrievedFromServer": 11,
      "memberType": "ApexClass",
      "isNameObsolete": false
    },
    "ApexClass__B2BAuthorizeTokenizedPaymentTest": {
      "serverRevisionCounter": 12,
      "lastRetrievedFromServer": 12,
      "memberType": "ApexClass",
      "isNameObsolete": false
    },
    "ApexClass__B2BCartControllerSample": {
      "serverRevisionCounter": 13,
      "lastRetrievedFromServer": 13,
      "memberType": "ApexClass",
      "isNameObsolete": false
    },
    "ApexClass__B2BGetInfo": {
      "serverRevisionCounter": 14,
      "lastRetrievedFromServer": 14,
      "memberType": "ApexClass",
      "isNameObsolete": false
    },
    "ApexClass__B2BPaymentController": {
      "serverRevisionCounter": 15,
      "lastRetrievedFromServer": 15,
      "memberType": "ApexClass",
      "isNameObsolete": false
    },
    "ApexClass__B2BPaymentControllerTest": {
      "serverRevisionCounter": 16,
      "lastRetrievedFromServer": 16,
      "memberType": "ApexClass",
      "isNameObsolete": false
    },
    "ApexClass__B2BSearchControllerSample": {
      "serverRevisionCounter": 17,
      "lastRetrievedFromServer": 17,
      "memberType": "ApexClass",
      "isNameObsolete": false
    },
    "ApexClass__B2BUtils": {
      "serverRevisionCounter": 18,
      "lastRetrievedFromServer": 18,
      "memberType": "ApexClass",
      "isNameObsolete": false
    },
    "LightningComponentBundle__billingAddressSelector": {
      "serverRevisionCounter": 19,
      "lastRetrievedFromServer": 19,
      "memberType": "LightningComponentBundle",
      "isNameObsolete": false
    },
    "LightningComponentBundle__cardPaymentMethod": {
      "serverRevisionCounter": 23,
      "lastRetrievedFromServer": 23,
      "memberType": "LightningComponentBundle",
      "isNameObsolete": false
    },
    "LightningComponentBundle__cartContents": {
      "serverRevisionCounter": 29,
      "lastRetrievedFromServer": 29,
      "memberType": "LightningComponentBundle",
      "isNameObsolete": false
    },
    "LightningComponentBundle__cartItems": {
      "serverRevisionCounter": 34,
      "lastRetrievedFromServer": 34,
      "memberType": "LightningComponentBundle",
      "isNameObsolete": false
    },
    "LightningComponentBundle__cartSummary": {
      "serverRevisionCounter": 39,
      "lastRetrievedFromServer": 39,
      "memberType": "LightningComponentBundle",
      "isNameObsolete": false
    },
    "LightningComponentBundle__cartUtils": {
      "serverRevisionCounter": 44,
      "lastRetrievedFromServer": 44,
      "memberType": "LightningComponentBundle",
      "isNameObsolete": false
    },
    "LightningComponentBundle__cmsResourceResolver": {
      "serverRevisionCounter": 47,
      "lastRetrievedFromServer": 47,
      "memberType": "LightningComponentBundle",
      "isNameObsolete": false
    },
    "LightningComponentBundle__navigationButtons": {
      "serverRevisionCounter": 50,
      "lastRetrievedFromServer": 50,
      "memberType": "LightningComponentBundle",
      "isNameObsolete": false
    },
    "LightningComponentBundle__paymentMethod": {
      "serverRevisionCounter": 54,
      "lastRetrievedFromServer": 54,
      "memberType": "LightningComponentBundle",
      "isNameObsolete": false
    },
    "LightningComponentBundle__productDetails": {
      "serverRevisionCounter": 60,
      "lastRetrievedFromServer": 60,
      "memberType": "LightningComponentBundle",
      "isNameObsolete": false
    },
    "LightningComponentBundle__productDetailsDisplay": {
      "serverRevisionCounter": 65,
      "lastRetrievedFromServer": 65,
      "memberType": "LightningComponentBundle",
      "isNameObsolete": false
    },
    "LightningComponentBundle__pubsub": {
      "serverRevisionCounter": 70,
      "lastRetrievedFromServer": 70,
      "memberType": "LightningComponentBundle",
      "isNameObsolete": false
    },
    "LightningComponentBundle__searchCard": {
      "serverRevisionCounter": 73,
      "lastRetrievedFromServer": 73,
      "memberType": "LightningComponentBundle",
      "isNameObsolete": false
    },
    "LightningComponentBundle__searchCategory": {
      "serverRevisionCounter": 78,
      "lastRetrievedFromServer": 78,
      "memberType": "LightningComponentBundle",
      "isNameObsolete": false
    },
    "LightningComponentBundle__searchFilter": {
      "serverRevisionCounter": 83,
      "lastRetrievedFromServer": 83,
      "memberType": "LightningComponentBundle",
      "isNameObsolete": false
    },
    "LightningComponentBundle__searchLayout": {
      "serverRevisionCounter": 88,
      "lastRetrievedFromServer": 88,
      "memberType": "LightningComponentBundle",
      "isNameObsolete": false
    },
    "LightningComponentBundle__searchPaginator": {
      "serverRevisionCounter": 93,
      "lastRetrievedFromServer": 93,
      "memberType": "LightningComponentBundle",
      "isNameObsolete": false
    },
    "LightningComponentBundle__searchResults": {
      "serverRevisionCounter": 98,
      "lastRetrievedFromServer": 98,
      "memberType": "LightningComponentBundle",
      "isNameObsolete": false
    },
    "LightningComponentResource__cartSummary/cartSummary.js-meta.xml": {
      "serverRevisionCounter": 40,
      "lastRetrievedFromServer": 40,
      "memberType": "LightningComponentResource",
      "isNameObsolete": false
    },
    "LightningComponentResource__cartSummary/cartSummary.css": {
      "serverRevisionCounter": 41,
      "lastRetrievedFromServer": 41,
      "memberType": "LightningComponentResource",
      "isNameObsolete": false
    },
    "LightningComponentResource__cartSummary/cartSummary.html": {
      "serverRevisionCounter": 42,
      "lastRetrievedFromServer": 42,
      "memberType": "LightningComponentResource",
      "isNameObsolete": false
    },
    "LightningComponentResource__cartSummary/cartSummary.js": {
      "serverRevisionCounter": 43,
      "lastRetrievedFromServer": 43,
      "memberType": "LightningComponentResource",
      "isNameObsolete": false
    },
    "LightningComponentResource__navigationButtons/navigationButtons.js": {
      "serverRevisionCounter": 51,
      "lastRetrievedFromServer": 51,
      "memberType": "LightningComponentResource",
      "isNameObsolete": false
    },
    "LightningComponentResource__navigationButtons/navigationButtons.js-meta.xml": {
      "serverRevisionCounter": 52,
      "lastRetrievedFromServer": 52,
      "memberType": "LightningComponentResource",
      "isNameObsolete": false
    },
    "LightningComponentResource__navigationButtons/navigationButtons.html": {
      "serverRevisionCounter": 53,
      "lastRetrievedFromServer": 53,
      "memberType": "LightningComponentResource",
      "isNameObsolete": false
    },
    "LightningComponentResource__cartContents/cartContents.js-meta.xml": {
      "serverRevisionCounter": 33,
      "lastRetrievedFromServer": 33,
      "memberType": "LightningComponentResource",
      "isNameObsolete": false
    },
    "LightningComponentResource__cartContents/cartContents.js": {
      "serverRevisionCounter": 32,
      "lastRetrievedFromServer": 32,
      "memberType": "LightningComponentResource",
      "isNameObsolete": false
    },
    "LightningComponentResource__cartContents/cartContents.css": {
      "serverRevisionCounter": 30,
      "lastRetrievedFromServer": 30,
      "memberType": "LightningComponentResource",
      "isNameObsolete": false
    },
    "LightningComponentResource__cartContents/cartContents.html": {
      "serverRevisionCounter": 31,
      "lastRetrievedFromServer": 31,
      "memberType": "LightningComponentResource",
      "isNameObsolete": false
    },
    "LightningComponentResource__cmsResourceResolver/cmsResourceResolver.js-meta.xml": {
      "serverRevisionCounter": 48,
      "lastRetrievedFromServer": 48,
      "memberType": "LightningComponentResource",
      "isNameObsolete": false
    },
    "LightningComponentResource__cmsResourceResolver/cmsResourceResolver.js": {
      "serverRevisionCounter": 49,
      "lastRetrievedFromServer": 49,
      "memberType": "LightningComponentResource",
      "isNameObsolete": false
    },
    "LightningComponentResource__searchLayout/searchLayout.js": {
      "serverRevisionCounter": 89,
      "lastRetrievedFromServer": 89,
      "memberType": "LightningComponentResource",
      "isNameObsolete": false
    },
    "LightningComponentResource__searchLayout/searchLayout.css": {
      "serverRevisionCounter": 90,
      "lastRetrievedFromServer": 90,
      "memberType": "LightningComponentResource",
      "isNameObsolete": false
    },
    "LightningComponentResource__searchLayout/searchLayout.js-meta.xml": {
      "serverRevisionCounter": 91,
      "lastRetrievedFromServer": 91,
      "memberType": "LightningComponentResource",
      "isNameObsolete": false
    },
    "LightningComponentResource__searchLayout/searchLayout.html": {
      "serverRevisionCounter": 92,
      "lastRetrievedFromServer": 92,
      "memberType": "LightningComponentResource",
      "isNameObsolete": false
    },
    "LightningComponentResource__searchCard/searchCard.js": {
      "serverRevisionCounter": 74,
      "lastRetrievedFromServer": 74,
      "memberType": "LightningComponentResource",
      "isNameObsolete": false
    },
    "LightningComponentResource__searchCard/searchCard.html": {
      "serverRevisionCounter": 75,
      "lastRetrievedFromServer": 75,
      "memberType": "LightningComponentResource",
      "isNameObsolete": false
    },
    "LightningComponentResource__searchCard/searchCard.js-meta.xml": {
      "serverRevisionCounter": 76,
      "lastRetrievedFromServer": 76,
      "memberType": "LightningComponentResource",
      "isNameObsolete": false
    },
    "LightningComponentResource__searchCard/searchCard.css": {
      "serverRevisionCounter": 77,
      "lastRetrievedFromServer": 77,
      "memberType": "LightningComponentResource",
      "isNameObsolete": false
    },
    "LightningComponentResource__billingAddressSelector/billingAddressSelector.html": {
      "serverRevisionCounter": 20,
      "lastRetrievedFromServer": 20,
      "memberType": "LightningComponentResource",
      "isNameObsolete": false
    },
    "LightningComponentResource__billingAddressSelector/billingAddressSelector.js": {
      "serverRevisionCounter": 21,
      "lastRetrievedFromServer": 21,
      "memberType": "LightningComponentResource",
      "isNameObsolete": false
    },
    "LightningComponentResource__billingAddressSelector/billingAddressSelector.js-meta.xml": {
      "serverRevisionCounter": 22,
      "lastRetrievedFromServer": 22,
      "memberType": "LightningComponentResource",
      "isNameObsolete": false
    },
    "LightningComponentResource__productDetails/productDetails.html": {
      "serverRevisionCounter": 61,
      "lastRetrievedFromServer": 61,
      "memberType": "LightningComponentResource",
      "isNameObsolete": false
    },
    "LightningComponentResource__productDetails/productDetails.js": {
      "serverRevisionCounter": 62,
      "lastRetrievedFromServer": 62,
      "memberType": "LightningComponentResource",
      "isNameObsolete": false
    },
    "LightningComponentResource__productDetails/productDetails.css": {
      "serverRevisionCounter": 63,
      "lastRetrievedFromServer": 63,
      "memberType": "LightningComponentResource",
      "isNameObsolete": false
    },
    "LightningComponentResource__productDetails/productDetails.js-meta.xml": {
      "serverRevisionCounter": 64,
      "lastRetrievedFromServer": 64,
      "memberType": "LightningComponentResource",
      "isNameObsolete": false
    },
    "LightningComponentResource__searchCategory/searchCategory.css": {
      "serverRevisionCounter": 79,
      "lastRetrievedFromServer": 79,
      "memberType": "LightningComponentResource",
      "isNameObsolete": false
    },
    "LightningComponentResource__searchCategory/searchCategory.js-meta.xml": {
      "serverRevisionCounter": 80,
      "lastRetrievedFromServer": 80,
      "memberType": "LightningComponentResource",
      "isNameObsolete": false
    },
    "LightningComponentResource__searchCategory/searchCategory.js": {
      "serverRevisionCounter": 81,
      "lastRetrievedFromServer": 81,
      "memberType": "LightningComponentResource",
      "isNameObsolete": false
    },
    "LightningComponentResource__searchCategory/searchCategory.html": {
      "serverRevisionCounter": 82,
      "lastRetrievedFromServer": 82,
      "memberType": "LightningComponentResource",
      "isNameObsolete": false
    },
    "LightningComponentResource__searchResults/searchResults.css": {
      "serverRevisionCounter": 99,
      "lastRetrievedFromServer": 99,
      "memberType": "LightningComponentResource",
      "isNameObsolete": false
    },
    "LightningComponentResource__searchResults/dataNormalizer.js": {
      "serverRevisionCounter": 100,
      "lastRetrievedFromServer": 100,
      "memberType": "LightningComponentResource",
      "isNameObsolete": false
    },
    "LightningComponentResource__searchResults/searchResults.js": {
      "serverRevisionCounter": 101,
      "lastRetrievedFromServer": 101,
      "memberType": "LightningComponentResource",
      "isNameObsolete": false
    },
    "LightningComponentResource__searchResults/searchResults.js-meta.xml": {
      "serverRevisionCounter": 102,
      "lastRetrievedFromServer": 102,
      "memberType": "LightningComponentResource",
      "isNameObsolete": false
    },
    "LightningComponentResource__searchResults/searchResults.html": {
      "serverRevisionCounter": 103,
      "lastRetrievedFromServer": 103,
      "memberType": "LightningComponentResource",
      "isNameObsolete": false
    },
    "LightningComponentResource__searchPaginator/searchPaginator.js-meta.xml": {
      "serverRevisionCounter": 94,
      "lastRetrievedFromServer": 94,
      "memberType": "LightningComponentResource",
      "isNameObsolete": false
    },
    "LightningComponentResource__searchPaginator/searchPaginator.html": {
      "serverRevisionCounter": 95,
      "lastRetrievedFromServer": 95,
      "memberType": "LightningComponentResource",
      "isNameObsolete": false
    },
    "LightningComponentResource__searchPaginator/searchPaginator.js": {
      "serverRevisionCounter": 96,
      "lastRetrievedFromServer": 96,
      "memberType": "LightningComponentResource",
      "isNameObsolete": false
    },
    "LightningComponentResource__searchPaginator/searchPaginator.css": {
      "serverRevisionCounter": 97,
      "lastRetrievedFromServer": 97,
      "memberType": "LightningComponentResource",
      "isNameObsolete": false
    },
    "LightningComponentResource__cartUtils/cartUtils.js-meta.xml": {
      "serverRevisionCounter": 45,
      "lastRetrievedFromServer": 45,
      "memberType": "LightningComponentResource",
      "isNameObsolete": false
    },
    "LightningComponentResource__cartUtils/cartUtils.js": {
      "serverRevisionCounter": 46,
      "lastRetrievedFromServer": 46,
      "memberType": "LightningComponentResource",
      "isNameObsolete": false
    },
    "LightningComponentResource__paymentMethod/constants.js": {
      "serverRevisionCounter": 55,
      "lastRetrievedFromServer": 55,
      "memberType": "LightningComponentResource",
      "isNameObsolete": false
    },
    "LightningComponentResource__paymentMethod/paymentMethod.js": {
      "serverRevisionCounter": 56,
      "lastRetrievedFromServer": 56,
      "memberType": "LightningComponentResource",
      "isNameObsolete": false
    },
    "LightningComponentResource__paymentMethod/paymentMethod.js-meta.xml": {
      "serverRevisionCounter": 57,
      "lastRetrievedFromServer": 57,
      "memberType": "LightningComponentResource",
      "isNameObsolete": false
    },
    "LightningComponentResource__paymentMethod/paymentMethod.html": {
      "serverRevisionCounter": 58,
      "lastRetrievedFromServer": 58,
      "memberType": "LightningComponentResource",
      "isNameObsolete": false
    },
    "LightningComponentResource__paymentMethod/paymentMethod.css": {
      "serverRevisionCounter": 59,
      "lastRetrievedFromServer": 59,
      "memberType": "LightningComponentResource",
      "isNameObsolete": false
    },
    "LightningComponentResource__productDetailsDisplay/productDetailsDisplay.js": {
      "serverRevisionCounter": 66,
      "lastRetrievedFromServer": 66,
      "memberType": "LightningComponentResource",
      "isNameObsolete": false
    },
    "LightningComponentResource__productDetailsDisplay/productDetailsDisplay.html": {
      "serverRevisionCounter": 67,
      "lastRetrievedFromServer": 67,
      "memberType": "LightningComponentResource",
      "isNameObsolete": false
    },
    "LightningComponentResource__productDetailsDisplay/productDetailsDisplay.css": {
      "serverRevisionCounter": 68,
      "lastRetrievedFromServer": 68,
      "memberType": "LightningComponentResource",
      "isNameObsolete": false
    },
    "LightningComponentResource__productDetailsDisplay/productDetailsDisplay.js-meta.xml": {
      "serverRevisionCounter": 69,
      "lastRetrievedFromServer": 69,
      "memberType": "LightningComponentResource",
      "isNameObsolete": false
    },
    "LightningComponentResource__cardPaymentMethod/cardPaymentMethod.css": {
      "serverRevisionCounter": 24,
      "lastRetrievedFromServer": 24,
      "memberType": "LightningComponentResource",
      "isNameObsolete": false
    },
    "LightningComponentResource__cardPaymentMethod/cardPaymentMethod.html": {
      "serverRevisionCounter": 25,
      "lastRetrievedFromServer": 25,
      "memberType": "LightningComponentResource",
      "isNameObsolete": false
    },
    "LightningComponentResource__cardPaymentMethod/cardPaymentMethod.js": {
      "serverRevisionCounter": 26,
      "lastRetrievedFromServer": 26,
      "memberType": "LightningComponentResource",
      "isNameObsolete": false
    },
    "LightningComponentResource__cardPaymentMethod/cardPaymentMethod.js-meta.xml": {
      "serverRevisionCounter": 27,
      "lastRetrievedFromServer": 27,
      "memberType": "LightningComponentResource",
      "isNameObsolete": false
    },
    "LightningComponentResource__cardPaymentMethod/constants.js": {
      "serverRevisionCounter": 28,
      "lastRetrievedFromServer": 28,
      "memberType": "LightningComponentResource",
      "isNameObsolete": false
    },
    "LightningComponentResource__cartItems/cartItems.html": {
      "serverRevisionCounter": 35,
      "lastRetrievedFromServer": 35,
      "memberType": "LightningComponentResource",
      "isNameObsolete": false
    },
    "LightningComponentResource__cartItems/cartItems.css": {
      "serverRevisionCounter": 36,
      "lastRetrievedFromServer": 36,
      "memberType": "LightningComponentResource",
      "isNameObsolete": false
    },
    "LightningComponentResource__cartItems/cartItems.js": {
      "serverRevisionCounter": 37,
      "lastRetrievedFromServer": 37,
      "memberType": "LightningComponentResource",
      "isNameObsolete": false
    },
    "LightningComponentResource__cartItems/cartItems.js-meta.xml": {
      "serverRevisionCounter": 38,
      "lastRetrievedFromServer": 38,
      "memberType": "LightningComponentResource",
      "isNameObsolete": false
    },
    "LightningComponentResource__pubsub/pubsub.js-meta.xml": {
      "serverRevisionCounter": 72,
      "lastRetrievedFromServer": 72,
      "memberType": "LightningComponentResource",
      "isNameObsolete": false
    },
    "LightningComponentResource__pubsub/pubsub.js": {
      "serverRevisionCounter": 71,
      "lastRetrievedFromServer": 71,
      "memberType": "LightningComponentResource",
      "isNameObsolete": false
    },
    "LightningComponentResource__searchFilter/searchFilter.html": {
      "serverRevisionCounter": 84,
      "lastRetrievedFromServer": 84,
      "memberType": "LightningComponentResource",
      "isNameObsolete": false
    },
    "LightningComponentResource__searchFilter/searchFilter.js": {
      "serverRevisionCounter": 85,
      "lastRetrievedFromServer": 85,
      "memberType": "LightningComponentResource",
      "isNameObsolete": false
    },
    "LightningComponentResource__searchFilter/searchFilter.css": {
      "serverRevisionCounter": 86,
      "lastRetrievedFromServer": 86,
      "memberType": "LightningComponentResource",
      "isNameObsolete": false
    },
    "LightningComponentResource__searchFilter/searchFilter.js-meta.xml": {
      "serverRevisionCounter": 87,
      "lastRetrievedFromServer": 87,
      "memberType": "LightningComponentResource",
      "isNameObsolete": false
    }
  }
}